<annotation>
	<folder>images</folder>
	<filename>0146_281.png</filename>
	<path>D:\Egien Elites\ICDAR 2019\GitHub Dataset\images\0146_281.png</path>
	<source>
		<database>Unknown</database>
	</source>
	<size>
		<width>2544</width>
		<height>3300</height>
		<depth>3</depth>
	</size>
	<segmented>0</segmented>
	<object>
		<name>table</name>
		<pose>Unspecified</pose>
		<truncated>0</truncated>
		<difficult>0</difficult>
		<bndbox>
			<xmin>704</xmin>
			<ymin>432</ymin>
			<xmax>1744</xmax>
			<ymax>1552</ymax>
		</bndbox>
	</object>
	<object>
		<name>table</name>
		<pose>Unspecified</pose>
		<truncated>0</truncated>
		<difficult>0</difficult>
		<bndbox>
			<xmin>705</xmin>
			<ymin>1746</ymin>
			<xmax>1800</xmax>
			<ymax>2440</ymax>
		</bndbox>
	</object>
</annotation>
