<annotation>
	<folder>Images</folder>
	<filename>10.1.1.190.2745_26.jpg</filename>
	<path>/media/devashish/Local Disk/Research/Projects/Table Project/Marmot 2020/Images/10.1.1.190.2745_26.jpg</path>
	<source>
		<database>Unknown</database>
	</source>
	<size>
		<width>794</width>
		<height>1123</height>
		<depth>1</depth>
	</size>
	<segmented>0</segmented>
	<object>
		<name>table</name>
		<pose>Unspecified</pose>
		<truncated>0</truncated>
		<difficult>0</difficult>
		<bndbox>
			<xmin>105</xmin>
			<ymin>98</ymin>
			<xmax>709</xmax>
			<ymax>634</ymax>
		</bndbox>
	</object>
</annotation>
