<annotation>
	<folder>Images</folder>
	<filename>18_42.jpg</filename>
	<path>/media/devashish/Local Disk/Research/Projects/Table Project/Marmot 2020/Images/18_42.jpg</path>
	<source>
		<database>Unknown</database>
	</source>
	<size>
		<width>794</width>
		<height>1126</height>
		<depth>1</depth>
	</size>
	<segmented>0</segmented>
	<object>
		<name>table</name>
		<pose>Unspecified</pose>
		<truncated>0</truncated>
		<difficult>0</difficult>
		<bndbox>
			<xmin>150</xmin>
			<ymin>163</ymin>
			<xmax>642</xmax>
			<ymax>334</ymax>
		</bndbox>
	</object>
</annotation>
