<annotation>
	<folder>Images</folder>
	<filename>52_274.jpg</filename>
	<path>/media/devashish/Local Disk/Research/Projects/Table Project/Marmot 2020/Images/52_274.jpg</path>
	<source>
		<database>Unknown</database>
	</source>
	<size>
		<width>448</width>
		<height>691</height>
		<depth>1</depth>
	</size>
	<segmented>0</segmented>
	<object>
		<name>table</name>
		<pose>Unspecified</pose>
		<truncated>0</truncated>
		<difficult>0</difficult>
		<bndbox>
			<xmin>14</xmin>
			<ymin>74</ymin>
			<xmax>430</xmax>
			<ymax>304</ymax>
		</bndbox>
	</object>
	<object>
		<name>table</name>
		<pose>Unspecified</pose>
		<truncated>0</truncated>
		<difficult>0</difficult>
		<bndbox>
			<xmin>13</xmin>
			<ymin>388</ymin>
			<xmax>432</xmax>
			<ymax>665</ymax>
		</bndbox>
	</object>
</annotation>
