<annotation>
	<folder>Images</folder>
	<filename>83_76.jpg</filename>
	<path>/media/devashish/Local Disk/Research/Projects/Table Project/Marmot 2020/Images/83_76.jpg</path>
	<source>
		<database>Unknown</database>
	</source>
	<size>
		<width>816</width>
		<height>1056</height>
		<depth>1</depth>
	</size>
	<segmented>0</segmented>
	<object>
		<name>table</name>
		<pose>Unspecified</pose>
		<truncated>0</truncated>
		<difficult>0</difficult>
		<bndbox>
			<xmin>187</xmin>
			<ymin>439</ymin>
			<xmax>666</xmax>
			<ymax>848</ymax>
		</bndbox>
	</object>
</annotation>
