<annotation>
	<folder>images</folder>
	<filename>9550_050.png</filename>
	<path>D:\Egien Elites\ICDAR 2019\GitHub Dataset\images\9550_050.png</path>
	<source>
		<database>Unknown</database>
	</source>
	<size>
		<width>3304</width>
		<height>2550</height>
		<depth>3</depth>
	</size>
	<segmented>0</segmented>
	<object>
		<name>table</name>
		<pose>Unspecified</pose>
		<truncated>0</truncated>
		<difficult>0</difficult>
		<bndbox>
			<xmin>990</xmin>
			<ymin>511</ymin>
			<xmax>3018</xmax>
			<ymax>807</ymax>
		</bndbox>
	</object>
	<object>
		<name>table</name>
		<pose>Unspecified</pose>
		<truncated>0</truncated>
		<difficult>0</difficult>
		<bndbox>
			<xmin>988</xmin>
			<ymin>928</ymin>
			<xmax>2729</xmax>
			<ymax>1478</ymax>
		</bndbox>
	</object>
	<object>
		<name>table</name>
		<pose>Unspecified</pose>
		<truncated>0</truncated>
		<difficult>0</difficult>
		<bndbox>
			<xmin>987</xmin>
			<ymin>1638</ymin>
			<xmax>3037</xmax>
			<ymax>1835</ymax>
		</bndbox>
	</object>
</annotation>
