
  <annotation>
    <folder>TRACKA</folder>
    <filename>cTDaR_t10350.jpg</filename>
    <path>/content/ICDAR2019_cTDaR/test/TRACKA/cTDaR_t10350.jpg</path>
    <source>
      <database>Unknown</database>
    </source>
    <size>
      <width>794</width>
      <height>1059</height>
      <depth>1</depth>
    </size>
    <segmented>0</segmented>	
      <object>
        <name>table</name>
        <pose>Unspecified</pose>
        <truncated>0</truncated>
        <difficult>0</difficult>
        <bndbox>
          <xmin>145</xmin>
          <ymin>123</ymin>
          <xmax>680</xmax>
          <ymax>229</ymax>
        </bndbox>
      </object>	
      <object>
        <name>table</name>
        <pose>Unspecified</pose>
        <truncated>0</truncated>
        <difficult>0</difficult>
        <bndbox>
          <xmin>145</xmin>
          <ymin>320</ymin>
          <xmax>680</xmax>
          <ymax>662</ymax>
        </bndbox>
      </object>	
      <object>
        <name>table</name>
        <pose>Unspecified</pose>
        <truncated>0</truncated>
        <difficult>0</difficult>
        <bndbox>
          <xmin>145</xmin>
          <ymin>735</ymin>
          <xmax>680</xmax>
          <ymax>841</ymax>
        </bndbox>
      </object>
</annotation>